[
  { "value": "Pacific/Midway", "label": "(UTC-11:00) Midway Island, Samoa" },
  { "value": "Pacific/Honolulu", "label": "(UTC-10:00) Hawaii" },
  { "value": "America/Anchorage", "label": "(UTC-09:00) Alaska" },
  { "value": "America/Los_Angeles", "label": "(UTC-08:00) Pacific Time — US & Canada" },
  { "value": "America/Tijuana", "label": "(UTC-08:00) Tijuana, Baja California" },
  { "value": "America/Denver", "label": "(UTC-07:00) Mountain Time — US & Canada" },
  { "value": "America/Phoenix", "label": "(UTC-07:00) Arizona" },
  { "value": "America/Chihuahua", "label": "(UTC-07:00) Chihuahua, Mazatlan" },
  { "value": "America/Chicago", "label": "(UTC-06:00) Central Time — US & Canada" },
  { "value": "America/Mexico_City", "label": "(UTC-06:00) Mexico City, Monterrey" },
  { "value": "America/Regina", "label": "(UTC-06:00) Saskatchewan" },
  { "value": "America/Guatemala", "label": "(UTC-06:00) Central America" },
  { "value": "America/New_York", "label": "(UTC-05:00) Eastern Time — US & Canada" },
  { "value": "America/Bogota", "label": "(UTC-05:00) Bogota, Lima, Quito" },
  { "value": "America/Indiana/Indianapolis", "label": "(UTC-05:00) Indiana (East)" },
  { "value": "America/Halifax", "label": "(UTC-04:00) Atlantic Time — Canada" },
  { "value": "America/Caracas", "label": "(UTC-04:00) Caracas" },
  { "value": "America/La_Paz", "label": "(UTC-04:00) La Paz" },
  { "value": "America/Manaus", "label": "(UTC-04:00) Manaus" },
  { "value": "America/Santiago", "label": "(UTC-04:00) Santiago" },
  { "value": "America/St_Johns", "label": "(UTC-03:30) Newfoundland" },
  { "value": "America/Sao_Paulo", "label": "(UTC-03:00) Brasilia" },
  { "value": "America/Argentina/Buenos_Aires", "label": "(UTC-03:00) Buenos Aires" },
  { "value": "America/Montevideo", "label": "(UTC-03:00) Montevideo" },
  { "value": "America/Cayenne", "label": "(UTC-03:00) Cayenne, Fortaleza" },
  { "value": "America/Godthab", "label": "(UTC-03:00) Greenland" },
  { "value": "America/Noronha", "label": "(UTC-02:00) Mid-Atlantic" },
  { "value": "Atlantic/Azores", "label": "(UTC-01:00) Azores" },
  { "value": "Atlantic/Cape_Verde", "label": "(UTC-01:00) Cape Verde Islands" },
  { "value": "UTC", "label": "(UTC+00:00) UTC" },
  { "value": "Europe/London", "label": "(UTC+00:00) London, Edinburgh, Dublin, Lisbon" },
  { "value": "Africa/Casablanca", "label": "(UTC+00:00) Casablanca, Monrovia, Reykjavik" },
  { "value": "Europe/Berlin", "label": "(UTC+01:00) Amsterdam, Berlin, Rome, Vienna" },
  { "value": "Europe/Belgrade", "label": "(UTC+01:00) Belgrade, Bratislava, Budapest, Prague" },
  { "value": "Europe/Brussels", "label": "(UTC+01:00) Brussels, Copenhagen, Madrid, Paris" },
  { "value": "Africa/Lagos", "label": "(UTC+01:00) West Central Africa" },
  { "value": "Europe/Sarajevo", "label": "(UTC+01:00) Sarajevo, Skopje, Warsaw, Zagreb" },
  { "value": "Europe/Athens", "label": "(UTC+02:00) Athens, Bucharest" },
  { "value": "Asia/Beirut", "label": "(UTC+02:00) Beirut" },
  { "value": "Africa/Cairo", "label": "(UTC+02:00) Cairo" },
  { "value": "Asia/Damascus", "label": "(UTC+02:00) Damascus" },
  { "value": "Africa/Harare", "label": "(UTC+02:00) Harare, Pretoria" },
  { "value": "Europe/Helsinki", "label": "(UTC+02:00) Helsinki, Kyiv, Riga, Sofia, Tallinn, Vilnius" },
  { "value": "Asia/Jerusalem", "label": "(UTC+02:00) Jerusalem" },
  { "value": "Europe/Minsk", "label": "(UTC+02:00) Minsk" },
  { "value": "Asia/Amman", "label": "(UTC+02:00) Amman" },
  { "value": "Asia/Baghdad", "label": "(UTC+03:00) Baghdad" },
  { "value": "Asia/Kuwait", "label": "(UTC+03:00) Kuwait, Riyadh" },
  { "value": "Europe/Moscow", "label": "(UTC+03:00) Moscow, St. Petersburg, Volgograd" },
  { "value": "Africa/Nairobi", "label": "(UTC+03:00) Nairobi" },
  { "value": "Asia/Tbilisi", "label": "(UTC+03:00) Tbilisi" },
  { "value": "Asia/Tehran", "label": "(UTC+03:30) Tehran" },
  { "value": "Asia/Muscat", "label": "(UTC+04:00) Abu Dhabi, Muscat" },
  { "value": "Asia/Baku", "label": "(UTC+04:00) Baku" },
  { "value": "Indian/Mauritius", "label": "(UTC+04:00) Port Louis" },
  { "value": "Asia/Yerevan", "label": "(UTC+04:00) Yerevan" },
  { "value": "Asia/Kabul", "label": "(UTC+04:30) Kabul" },
  { "value": "Asia/Karachi", "label": "(UTC+05:00) Islamabad, Karachi" },
  { "value": "Asia/Tashkent", "label": "(UTC+05:00) Tashkent, Ashgabat" },
  { "value": "Asia/Yekaterinburg", "label": "(UTC+05:00) Yekaterinburg" },
  { "value": "Asia/Kolkata", "label": "(UTC+05:30) Chennai, Kolkata, Mumbai, New Delhi" },
  { "value": "Asia/Colombo", "label": "(UTC+05:30) Sri Jayawardenepura" },
  { "value": "Asia/Kathmandu", "label": "(UTC+05:45) Kathmandu" },
  { "value": "Asia/Dhaka", "label": "(UTC+06:00) Astana, Dhaka" },
  { "value": "Asia/Almaty", "label": "(UTC+06:00) Almaty, Novosibirsk" },
  { "value": "Asia/Rangoon", "label": "(UTC+06:30) Yangon (Rangoon)" },
  { "value": "Asia/Bangkok", "label": "(UTC+07:00) Bangkok, Hanoi, Jakarta" },
  { "value": "Asia/Krasnoyarsk", "label": "(UTC+07:00) Krasnoyarsk" },
  { "value": "Asia/Hong_Kong", "label": "(UTC+08:00) Beijing, Chongqing, Hong Kong, Urumqi" },
  { "value": "Asia/Irkutsk", "label": "(UTC+08:00) Irkutsk" },
  { "value": "Asia/Kuala_Lumpur", "label": "(UTC+08:00) Kuala Lumpur, Singapore" },
  { "value": "Australia/Perth", "label": "(UTC+08:00) Perth" },
  { "value": "Asia/Taipei", "label": "(UTC+08:00) Taipei" },
  { "value": "Asia/Ulaanbaatar", "label": "(UTC+08:00) Ulaanbaatar" },
  { "value": "Asia/Tokyo", "label": "(UTC+09:00) Osaka, Sapporo, Tokyo" },
  { "value": "Asia/Seoul", "label": "(UTC+09:00) Seoul" },
  { "value": "Asia/Yakutsk", "label": "(UTC+09:00) Yakutsk" },
  { "value": "Australia/Adelaide", "label": "(UTC+09:30) Adelaide" },
  { "value": "Australia/Darwin", "label": "(UTC+09:30) Darwin" },
  { "value": "Australia/Brisbane", "label": "(UTC+10:00) Brisbane" },
  { "value": "Australia/Sydney", "label": "(UTC+10:00) Canberra, Melbourne, Sydney" },
  { "value": "Pacific/Guam", "label": "(UTC+10:00) Guam, Port Moresby" },
  { "value": "Australia/Hobart", "label": "(UTC+10:00) Hobart" },
  { "value": "Asia/Vladivostok", "label": "(UTC+10:00) Vladivostok" },
  { "value": "Asia/Magadan", "label": "(UTC+11:00) Magadan, Solomon Islands, New Caledonia" },
  { "value": "Pacific/Auckland", "label": "(UTC+12:00) Auckland, Wellington" },
  { "value": "Pacific/Fiji", "label": "(UTC+12:00) Fiji, Kamchatka, Marshall Islands" },
  { "value": "Pacific/Tongatapu", "label": "(UTC+13:00) Nuku'alofa" },
  { "value": "Pacific/Apia", "label": "(UTC+13:00) Samoa" }
]